automation_report/report.html
automation_report/report.py
automation_report-1.0.2.dist-info/LICENSE
automation_report-1.0.2.dist-info/METADATA
automation_report-1.0.2.dist-info/WHEEL
automation_report-1.0.2.dist-info/top_level.txt
automation_report-1.0.2.dist-info/RECORD
