Metadata-Version: 2.1
Name: automation-report
Version: 1.0.2
Summary: Simple report for your test automation including various cases/steps specifying its valid status.
Home-page: https://github.com/bibekad123/automation-report
Author: Bibek Adhikari
Author-email: bbekad94@gmail.com
License: MIT
Download-URL: https://github.com/bibekad123/automation-report/archive/1.0.1.tar.gz
Keywords: automation report,report,automation
Platform: UNKNOWN
Classifier: Development Status :: 5 - Production/Stable
Classifier: Intended Audience :: Developers
Classifier: Topic :: Software Development
Classifier: License :: OSI Approved :: MIT License
Classifier: Programming Language :: Python :: 3
Classifier: Programming Language :: Python :: 3.7
